[{"json":"{\"time\":1668995846416,\"message\":\"{\\\"receiver\\\":1,\\\"sender\\\":2,\\\"channel\\\":\\\"friend\\\",\\\"time\\\":1668995846416,\\\"type\\\":\\\"text\\\",\\\"content\\\":\\\"222\\\"}\"}","message":{"channel":"friend","content":"222","json":"{\"receiver\":1,\"sender\":2,\"channel\":\"friend\",\"time\":1668995846416,\"type\":\"text\",\"content\":\"222\"}","receiver":1,"sender":2,"time":1668995846416,"type":"text"},"timestamp":1668995846416},{"json":"{\"time\":1668997024376,\"message\":\"{\\\"receiver\\\":2,\\\"sender\\\":1,\\\"channel\\\":\\\"friend\\\",\\\"time\\\":1668997024376,\\\"type\\\":\\\"file\\\",\\\"content\\\":\\\"geogebra-export.png\\\"}\"}","message":{"channel":"friend","content":"geogebra-export.png","json":"{\"receiver\":2,\"sender\":1,\"channel\":\"friend\",\"time\":1668997024376,\"type\":\"file\",\"content\":\"geogebra-export.png\"}","receiver":2,"sender":1,"time":1668997024376,"type":"file"},"timestamp":1668997024376},{"json":"{\"time\":1668998418159,\"message\":\"{\\\"receiver\\\":1,\\\"sender\\\":2,\\\"channel\\\":\\\"friend\\\",\\\"time\\\":1668998418159,\\\"type\\\":\\\"file\\\",\\\"content\\\":\\\"4366908.png\\\"}\"}","message":{"channel":"friend","content":"4366908.png","json":"{\"receiver\":1,\"sender\":2,\"channel\":\"friend\",\"time\":1668998418159,\"type\":\"file\",\"content\":\"4366908.png\"}","receiver":1,"sender":2,"time":1668998418159,"type":"file"},"timestamp":1668998418159},{"json":"{\"time\":1668995860525,\"message\":\"{\\\"receiver\\\":2,\\\"sender\\\":1,\\\"channel\\\":\\\"friend\\\",\\\"time\\\":1668995860525,\\\"type\\\":\\\"file\\\",\\\"content\\\":\\\"演讲小抄.md\\\"}\"}","message":{"channel":"friend","content":"演讲小抄.md","json":"{\"receiver\":2,\"sender\":1,\"channel\":\"friend\",\"time\":1668995860525,\"type\":\"file\",\"content\":\"演讲小抄.md\"}","receiver":2,"sender":1,"time":1668995860525,"type":"file"},"timestamp":1668995860525}]